rds_snap/__init__.py
rds_snap/__main__.py
rds_snap/version.py
rds_snap/commands/__init__.py
rds_snap/commands/cluster.py
rds_snap/commands/snapshot.py
rds_snap/commands/utils.py
rds_snap/commands/waiters.py
rds_snap-0.1.0.dist-info/LICENSE
rds_snap-0.1.0.dist-info/METADATA
rds_snap-0.1.0.dist-info/WHEEL
rds_snap-0.1.0.dist-info/dependency_links.txt
rds_snap-0.1.0.dist-info/entry_points.txt
rds_snap-0.1.0.dist-info/top_level.txt
rds_snap-0.1.0.dist-info/RECORD
