Metadata-Version: 2.1
Name: rds-snap
Version: 0.1.0
Summary: Tool to allow for the management of aws rds aurora snapshots and clusters.
Home-page: https://github.com/RingierIMU/rds-snap
Author: Ringier Tech
Author-email: tools@ringier.co.za
License: UNKNOWN
Keywords: aws,rds,aurora,snapshot,cluster
Platform: UNKNOWN
Classifier: Programming Language :: Python :: 3
Classifier: License :: OSI Approved :: MIT License
Classifier: Operating System :: OS Independent
Requires-Python: >=3
Requires-Dist: click
Requires-Dist: click-log
Requires-Dist: boto3
